musamusa_mustextfile/aboutproject.py
musamusa_mustextfile/contexts/default.json
musamusa_mustextfile/mustextfile.py
musamusa_mustextfile-0.0.1.dist-info/LICENSE
musamusa_mustextfile-0.0.1.dist-info/WHEEL
musamusa_mustextfile-0.0.1.dist-info/METADATA
musamusa_mustextfile-0.0.1.dist-info/RECORD
