Metadata-Version: 2.1
Name: musamusa-mustextfile
Version: 0.0.1
Summary: .mus -> AnnotatedText
License: GPLv3
Author: suizokukan
Author-email: suizokukan@orange.fr
Requires-Python: >=3.9,<4.0
Classifier: License :: Other/Proprietary License
Classifier: Programming Language :: Python :: 3
Classifier: Programming Language :: Python :: 3.9
